simple_gomoku/__init__.py
simple_gomoku/env/Gomoku.py
simple_gomoku/env/TicTacToe.py
simple_gomoku/env/__init__.py
simple_gomoku-2.2.1.dist-info/METADATA
simple_gomoku-2.2.1.dist-info/WHEEL
simple_gomoku-2.2.1.dist-info/top_level.txt
simple_gomoku-2.2.1.dist-info/RECORD
